chrisbrake/__init__.py
chrisbrake/__main__.py
chrisbrake/io/__init__.py
chrisbrake/io/rec/__init__.py
chrisbrake/io/rec/__main__.py
chrisbrake-0.0.2.dist-info/entry_points.txt
chrisbrake-0.0.2.dist-info/LICENSE
chrisbrake-0.0.2.dist-info/WHEEL
chrisbrake-0.0.2.dist-info/METADATA
chrisbrake-0.0.2.dist-info/RECORD
