Metadata-Version: 2.1
Name: chrisbrake
Version: 0.0.2
Summary: chrisbrake 
Home-page: https://github.com/chrisbrake/chrisbrake
License: UNKNOWN
Author: Chris Brake
Author-email: chris.brake@gmail.com
Classifier: License :: OSI Approved :: BSD License
Classifier: Programming Language :: Python :: 3
Requires-Dist: pynput
Requires-Dist: sphinx; extra == "doc"
Requires-Dist: flake8; extra == "test"
Requires-Dist: pytest; extra == "test"
Requires-Dist: pytest-cov; extra == "test"
Provides-Extra: doc
Provides-Extra: test
